Workbook

Sheet Report Map
A1: Finance Ops Ledger Review: data workbook
A2: This workbook is the source of every number in the interactive report. Each figure below links to the cell that calculates it.
A3: FICTIONAL TEST DATA: 30 invoices from the Finance Ops Agent Stage 4 test (data/stage4_test.db). Not a real company's accounts.
A5: Report section | B5: Figure shown in the report | C5: Value | D5: Source cell
A6: Top row | B6: Approved September spend (IQD) | C6: =Summary!C5 -> 7715000 | D6: Summary → C5
A7: Top row | B7: Change vs August | C7: =Summary!C7 -> 0.011140236 | D7: Summary → C7
A8: Top row | B8: Approved September spend (USD) | C8: =Summary!C8 -> 2150.5 | D8: Summary → C8
A9: Top row | B9: Waiting for a decision (IQD) | C9: =Summary!C11 -> 7438000 | D9: Summary → C11
A10: Top row | B10: Duplicate payment blocked (IQD) | C10: =Summary!C14 -> 1060000 | D10: Summary → C14
A11: Top row | B11: Fields read correctly | C11: =Summary!C16 -> 90 | D11: Summary → C16
A12: 1 · Decision queue | B12: P-0018 Babel amount | C12: ='Decision Queue'!D5 -> 6750000 | D12: Decision Queue → D5
A13: 1 · Decision queue | B13: P-0024 Al-Nakheel amount | C13: ='Decision Queue'!D6 -> 488000 | D13: Decision Queue → D6
A14: 1 · Decision queue | B14: P-0025 Al-Amin amount | C14: ='Decision Queue'!D7 -> 200000 | D14: Decision Queue → D7
A15: 2 · What-if | B15: Projected September (with your Y/N choices) | C15: ='Decision Queue'!D12 -> 7715000 | D15: Decision Queue → D12
A16: 3 · Timeline | B16: Number of invoices (one dot each) | C16: =COUNTA(Invoices!A5:A34) -> 30 | D16: Invoices → A5
A17: 4 · Monthly by category | B17: Total IQD, September | C17: ='Monthly by Category'!E13 -> 7715000 | D17: Monthly by Category → E13
A18: 4 · Monthly by category | B18: Total IQD, August | C18: ='Monthly by Category'!D13 -> 7630000 | D18: Monthly by Category → D13
A19: 4 · Monthly by category | B19: Total IQD, July | C19: ='Monthly by Category'!C13 -> 5770000 | D19: Monthly by Category → C13
A20: 5 · USD spend | B20: USD, September | C20: ='Monthly by Category'!E19 -> 2150.5 | D20: Monthly by Category → E19
A21: 6 · Suppliers | B21: Babel approved total | C21: =Suppliers!D5 -> 7275000 | D21: Suppliers → D5
A22: 6 · Suppliers | B22: Total approved IQD, Jun–Sep | C22: =Suppliers!D13 -> 21985000 | D22: Suppliers → D13
A23: 7 · Supplier × month | B23: Babel, September (one cell of the grid) | C23: =Suppliers!M5 -> 1025000 | D23: Suppliers → M5
A24: 8 · Control checks | B24: Total warnings, September | C24: ='Control Checks'!C13 -> 5 | D24: Control Checks → C13
A25: 9 · Strategy | B25: Fixed monthly IQD (generator + internet) | C25: ='Recurring Costs'!G10 -> 1371000 | D25: Recurring Costs → G10
A27: Sheets
A28: Invoices | B28: Source data: one row per invoice. Every other sheet calculates from here.
A29: Line Items | B29: Items on each September invoice, with an add-up check.
A30: Summary | B30: Key figures (report top row).
A31: Monthly by Category | B31: Report sections 4 and 5.
A32: Suppliers | B32: Report sections 6 and 7.
A33: Decision Queue | B33: Report sections 1 and 2, with an editable what-if.
A34: Control Checks | B34: Report section 8.
A35: Recurring Costs | B35: Report section 9, strategy decision 5.
A37: Colour key: blue = value from the ledger or an input · black = formula · green = link to another sheet · yellow = cell you may edit.

Sheet Invoices
A1: Invoice register (source data)
A2: One row per invoice, exported from data/stage4_test.db (pending + ledger tables). FICTIONAL TEST DATA. Blue = values from the ledger; black = formulas.
A4: Ref | B4: Ledger ID | C4: Supplier (Arabic) | D4: Supplier | E4: Category | F4: Invoice no. | G4: Tax no. | H4: Invoice date | I4: Month | J4: Weekday | K4: Currency | L4: Amount | M4: Status | N4: Batch | O4: Source file | P4: Decided by | Q4: Decision note | R4: Warning at staging | S4: Warning detail
A5: P-0010 | B5: L-0010 | C5: مولدة أور الأهلية | D5: Ur Generator | E5: Utilities | F5: UR-06-2026-098 | G5: 300660913 | H5: 46176 | I5: =YEAR(H5)&"-"&TEXT(MONTH(H5),"00") -> 2026-06 | J5: =TEXT(H5,"dddd") -> Wednesday | K5: IQD | L5: 870000 | M5: approved | N5: Seed history | O5: seed: prior months | P5: seed history (test)
A6: P-0011 | B6: L-0011 | C6: مولدة أور الأهلية | D6: Ur Generator | E6: Utilities | F6: UR-07-2026-104 | G6: 300660913 | H6: 46205 | I6: =YEAR(H6)&"-"&TEXT(MONTH(H6),"00") -> 2026-07 | J6: =TEXT(H6,"dddd") -> Thursday | K6: IQD | L6: 900000 | M6: approved | N6: Seed history | O6: seed: prior months | P6: seed history (test)
A7: P-0001 | B7: L-0001 | C7: شركة دجلة للتجهيزات المكتبية | D7: Dijla Office Supplies | E7: Office supplies | F7: DJ-2026-0611 | G7: 300418275 | H7: 46210 | I7: =YEAR(H7)&"-"&TEXT(MONTH(H7),"00") -> 2026-07 | J7: =TEXT(H7,"dddd") -> Tuesday | K7: IQD | L7: 1150000 | M7: approved | N7: Seed history | O7: seed: prior months | P7: seed history (test)
A8: P-0013 | B8: L-0013 | C8: Gulf Bridge IT Trading LLC | D8: Gulf Bridge IT | E8: IT (USD) | F8: GB-INV-54710 | G8: 100234567800003 | H8: 46212 | I8: =YEAR(H8)&"-"&TEXT(MONTH(H8),"00") -> 2026-07 | J8: =TEXT(H8,"dddd") -> Thursday | K8: USD | L8: 1180 | M8: approved | N8: Seed history | O8: seed: prior months | P8: seed history (test)
A9: P-0004 | B9: L-0004 | C9: مؤسسة النخيل للمواد الغذائية | D9: Al-Nakheel Foodstuffs | E9: Pantry | F9: NK/1031 | G9: 300552190 | H9: 46216 | I9: =YEAR(H9)&"-"&TEXT(MONTH(H9),"00") -> 2026-07 | J9: =TEXT(H9,"dddd") -> Monday | K9: IQD | L9: 640000 | M9: approved | N9: Seed history | O9: seed: prior months | P9: seed history (test)
A10: P-0007 | B10: L-0007 | C10: شركة بابل للمقاولات والصيانة | D10: Babel Maintenance | E10: Maintenance | F10: BB-0331 | G10: 300731044 | H10: 46218 | I10: =YEAR(H10)&"-"&TEXT(MONTH(H10),"00") -> 2026-07 | J10: =TEXT(H10,"dddd") -> Wednesday | K10: IQD | L10: 2100000 | M10: approved | N10: Seed history | O10: seed: prior months | P10: seed history (test)
A11: P-0002 | B11: L-0002 | C11: شركة دجلة للتجهيزات المكتبية | D11: Dijla Office Supplies | E11: Office supplies | F11: DJ-2026-0688 | G11: 300418275 | H11: 46225 | I11: =YEAR(H11)&"-"&TEXT(MONTH(H11),"00") -> 2026-07 | J11: =TEXT(H11,"dddd") -> Wednesday | K11: IQD | L11: 980000 | M11: approved | N11: Seed history | O11: seed: prior months | P11: seed history (test)
A12: P-0005 | B12: L-0005 | C12: مؤسسة النخيل للمواد الغذائية | D12: Al-Nakheel Foodstuffs | E12: Pantry | F12: NK/1092 | G12: 300552190 | H12: 46237 | I12: =YEAR(H12)&"-"&TEXT(MONTH(H12),"00") -> 2026-08 | J12: =TEXT(H12,"dddd") -> Monday | K12: IQD | L12: 585000 | M12: approved | N12: Seed history | O12: seed: prior months | P12: seed history (test)
A13: P-0012 | B13: L-0012 | C13: مولدة أور الأهلية | D13: Ur Generator | E13: Utilities | F13: UR-08-2026-111 | G13: 300660913 | H13: 46238 | I13: =YEAR(H13)&"-"&TEXT(MONTH(H13),"00") -> 2026-08 | J13: =TEXT(H13,"dddd") -> Tuesday | K13: IQD | L13: 945000 | M13: approved | N13: Seed history | O13: seed: prior months | P13: seed history (test)
A14: P-0008 | B14: L-0008 | C14: شركة بابل للمقاولات والصيانة | D14: Babel Maintenance | E14: Maintenance | F14: BB-0352 | G14: 300731044 | H14: 46239 | I14: =YEAR(H14)&"-"&TEXT(MONTH(H14),"00") -> 2026-08 | J14: =TEXT(H14,"dddd") -> Wednesday | K14: IQD | L14: 1850000 | M14: approved | N14: Seed history | O14: seed: prior months | P14: seed history (test)
A15: P-0014 | B15: L-0014 | C15: Gulf Bridge IT Trading LLC | D15: Gulf Bridge IT | E15: IT (USD) | F15: GB-INV-54866 | G15: 100234567800003 | H15: 46240 | I15: =YEAR(H15)&"-"&TEXT(MONTH(H15),"00") -> 2026-08 | J15: =TEXT(H15,"dddd") -> Thursday | K15: USD | L15: 1320.5 | M15: approved | N15: Seed history | O15: seed: prior months | P15: seed history (test)
A16: P-0003 | B16: L-0003 | C16: شركة دجلة للتجهيزات المكتبية | D16: Dijla Office Supplies | E16: Office supplies | F16: DJ-2026-0794 | G16: 300418275 | H16: 46245 | I16: =YEAR(H16)&"-"&TEXT(MONTH(H16),"00") -> 2026-08 | J16: =TEXT(H16,"dddd") -> Tuesday | K16: IQD | L16: 1240000 | M16: approved | N16: Seed history | O16: seed: prior months | P16: seed history (test)
... A19: P-0009 | B19: L-0009 | C19: شركة بابل للمقاولات والصيانة | D19: Babel Maintenance | E19: Maintenance | F19: BB-0377 | G19: 300731044 | H19: 46260 | I19: =YEAR(H19)&"-"&TEXT(MONTH(H19),"00") -> 2026-08 | J19: =TEXT(H19,"dddd") -> Wednesday | K19: IQD | L19: 2300000 | M19: approved | N19: Seed history | O19: seed: prior months | P19: seed history (test)
A20: P-0019 | B20: L-0018 | C20: مولدة أور الأهلية | D20: Ur Generator | E20: Utilities | F20: UR-09-2026-117 | G20: 300660913 | H20: 46266 | I20: =YEAR(H20)&"-"&TEXT(MONTH(H20),"00") -> 2026-09 | J20: =TEXT(H20,"dddd") -> Tuesday | K20: IQD | L20: 896000 | M20: approved | N20: September sample | O20: samples/inv04_ur_generator.jpg | P20: Test manager (simulated, Stage 4) | Q20: clean / verified (test)
A21: P-0027 | B21: L-0023 | C21: شركة نبض الشبكة لخدمات الإنترنت | D21: Nabd Internet | E21: Utilities | F21: NB-77310 | G21: 300927358 | H21: 46267 | I21: =YEAR(H21)&"-"&TEXT(MONTH(H21),"00") -> 2026-09 | J21: =TEXT(H21,"dddd") -> Wednesday | K21: IQD | L21: 475000 | M21: approved | N21: September sample | O21: samples/inv12_nabd_internet.pdf | P21: Test manager (simulated, Stage 4) | Q21: clean / verified (test)
A22: P-0016 | B22: L-0016 | C22: شركة دجلة للتجهيزات المكتبية | D22: Dijla Office Supplies | E22: Office supplies | F22: DJ-2026-0917 | G22: 300418275 | H22: 46271 | I22: =YEAR(H22)&"-"&TEXT(MONTH(H22),"00") -> 2026-09 | J22: =TEXT(H22,"dddd") -> Sunday | K22: IQD | L22: 950000 | M22: approved | N22: September sample | O22: samples/inv01_dijla.pdf | P22: Test manager (simulated, Stage 4) | Q22: clean / verified (test)
A23: P-0017 | B23: L-0017 | C23: مؤسسة النخيل للمواد الغذائية | D23: Al-Nakheel Foodstuffs | E23: Pantry | F23: NK/1184 | G23: 300552190 | H23: 46272 | I23: =YEAR(H23)&"-"&TEXT(MONTH(H23),"00") -> 2026-09 | J23: =TEXT(H23,"dddd") -> Monday | K23: IQD | L23: 521000 | M23: approved | N23: September sample | O23: samples/inv02_nakheel.pdf | P23: Test manager (simulated, Stage 4) | Q23: clean / verified (test)
A24: P-0018 | C24: شركة بابل للمقاولات والصيانة | D24: Babel Maintenance | E24: Maintenance | F24: BB-0392 | G24: 300731044 | H24: 46273 | I24: =YEAR(H24)&"-"&TEXT(MONTH(H24),"00") -> 2026-09 | J24: =TEXT(H24,"dddd") -> Tuesday | K24: IQD | L24: 6750000 | M24: pending | N24: September sample | O24: samples/inv03_babel.pdf | R24: Unusually large | S24: 3.2x supplier average of 2,083,333 IQD
A25: P-0020 | B25: L-0019 | C25: Gulf Bridge IT Trading LLC | D25: Gulf Bridge IT | E25: IT (USD) | F25: GB-INV-55021 | G25: 100234567800003 | H25: 46274 | I25: =YEAR(H25)&"-"&TEXT(MONTH(H25),"00") -> 2026-09 | J25: =TEXT(H25,"dddd") -> Wednesday | K25: USD | L25: 1208 | M25: approved | N25: September sample | O25: samples/inv05_gulfbridge.pdf | P25: Test manager (simulated, Stage 4) | Q25: clean / verified (test)
A26: P-0026 | B26: L-0022 | C26: مطبعة المنصور الحديثة | D26: Al-Mansour Press | E26: Printing & marketing | F26: MP-2291 | G26: 300814467 | H26: 46275 | I26: =YEAR(H26)&"-"&TEXT(MONTH(H26),"00") -> 2026-09 | J26: =TEXT(H26,"dddd") -> Thursday | K26: IQD | L26: 800000 | M26: approved | N26: September sample | O26: samples/inv11_mansour_press.pdf | P26: Test manager (simulated, Stage 4) | Q26: clean / verified (test)
A27: P-0021 | B27: L-0020 | C27: شركة دجلة للتجهيزات المكتبية | D27: Dijla Office Supplies | E27: Office supplies | F27: DJ-2026-0952 | G27: 300418275 | H27: 46281 | I27: =YEAR(H27)&"-"&TEXT(MONTH(H27),"00") -> 2026-09 | J27: =TEXT(H27,"dddd") -> Wednesday | K27: IQD | L27: 1060000 | M27: approved | N27: September sample | O27: samples/inv06_dijla.pdf | P27: Test manager (simulated, Stage 4) | Q27: clean / verified (test)
A28: P-0022 | C28: شركة دجلة للتجهيزات المكتبية | D28: Dijla Office Supplies | E28: Office supplies | F28: DJ-2026-0952 | G28: 300418275 | H28: 46281 | I28: =YEAR(H28)&"-"&TEXT(MONTH(H28),"00") -> 2026-09 | J28: =TEXT(H28,"dddd") -> Wednesday | K28: IQD | L28: 1060000 | M28: rejected | N28: September sample | O28: samples/inv07_dijla_photo.jpg | P28: Test manager (simulated, Stage 4) | Q28: Duplicate of P-0021 (photo of same invoice) | R28: Exact duplicate | S28: Same invoice no. DJ-2026-0952 as P-0021 (photo of same paper invoice)
A29: P-0025 | C29: ورشة الأمين لتصليح السيارات | D29: Al-Amin Auto Workshop | E29: Vehicles | F29: ٠٤٣١ | G29: MISSING | H29: 46283 | I29: =YEAR(H29)&"-"&TEXT(MONTH(H29),"00") -> 2026-09 | J29: =TEXT(H29,"dddd") -> Friday | K29: IQD | L29: 200000 | M29: pending | N29: September sample | O29: samples/inv10_amin_workshop.jpg | R29: Weekend date; No tax number | S29: Friday 18 Sep 2026; no tax number printed; new supplier
A30: P-0023 | B30: L-0021 | C30: مؤسسة النخيل للمواد الغذائية | D30: Al-Nakheel Foodstuffs | E30: Pantry | F30: NK/1207 | G30: 300552190 | H30: 46286 | I30: =YEAR(H30)&"-"&TEXT(MONTH(H30),"00") -> 2026-09 | J30: =TEXT(H30,"dddd") -> Monday | K30: IQD | L30: 488000 | M30: approved | N30: September sample | O30: samples/inv08_nakheel.pdf | P30: Test manager (simulated, Stage 4) | Q30: clean / verified (test)
A31: P-0028 | B31: L-0024 | C31: شركة بابل للمقاولات والصيانة | D31: Babel Maintenance | E31: Maintenance | F31: BB-0401 | G31: 300731044 | H31: 46287 | I31: =YEAR(H31)&"-"&TEXT(MONTH(H31),"00") -> 2026-09 | J31: =TEXT(H31,"dddd") -> Tuesday | K31: IQD | L31: 1025000 | M31: approved | N31: September sample | O31: samples/inv13_babel.pdf | P31: Test manager (simulated, Stage 4) | Q31: clean / verified (test)
A32: P-0024 | C32: مؤسسة النخيل للمواد الغذائية | D32: Al-Nakheel Foodstuffs | E32: Pantry | F32: NK/1213 | G32: 300552190 | H32: 46288 | I32: =YEAR(H32)&"-"&TEXT(MONTH(H32),"00") -> 2026-09 | J32: =TEXT(H32,"dddd") -> Wednesday | K32: IQD | L32: 488000 | M32: pending | N32: September sample | O32: samples/inv09_nakheel.pdf | R32: Probable duplicate | S32: Same supplier & amount as P-0023, 2 days apart, identical items
A33: P-0029 | B33: L-0025 | C33: Gulf Bridge IT Trading LLC | D33: Gulf Bridge IT | E33: IT (USD) | F33: GB-INV-55108 | G33: 100234567800003 | H33: 46289 | I33: =YEAR(H33)&"-"&TEXT(MONTH(H33),"00") -> 2026-09 | J33: =TEXT(H33,"dddd") -> Thursday | K33: USD | L33: 942.5 | M33: approved | N33: September sample | O33: samples/inv14_gulfbridge.pdf | P33: Test manager (simulated, Stage 4) | Q33: clean / verified (test)
A34: P-0030 | B34: L-0026 | C34: مكتب الكرخ للاستشارات المحاسبية | D34: Al-Karkh Accounting | E34: Professional fees | F34: KA-2026-031 | G34: 300349902 | H34: 46294 | I34: =YEAR(H34)&"-"&TEXT(MONTH(H34),"00") -> 2026-09 | J34: =TEXT(H34,"dddd") -> Tuesday | K34: IQD | L34: 1500000 | M34: approved | N34: September sample | O34: samples/inv15_karkh_accounting.pdf | P34: Test manager (simulated, Stage 4) | Q34: clean / verified (test)
A36: Notes
A37: USD amounts stored in the ledger in cents; shown here in dollars. IQD and USD are never converted or added together.
A38: Orange rows = waiting for approval (not counted in totals). Red row = rejected (kept on record, never deleted).
A39: Categories assigned per supplier for this review; they are not stored in the ledger.

Sheet Line Items
A1: Invoice line items (September sample invoices)
A2: From items_json in the ledger. The check column proves the lines add up to each invoice total.
A4: Ref | B4: Supplier | C4: Item (Arabic) | D4: Qty | E4: Line total | F4: Currency | H4: Ref | I4: Sum of lines | J4: Invoice amount | K4: Difference | L4: Check
A5: P-0019 | B5: Ur Generator | C5: اشتراك مولدة - شهر آب (أمبير) | D5: 32 | E5: 896000 | F5: IQD | H5: P-0019 | I5: =SUMIFS($E$5:$E$46,$A$5:$A$46,H5) -> 896000 | J5: =INDEX(Invoices!$L$5:$L$34,MATCH(H5,Invoices!$A$5:$A$34,0)) -> 896000 | K5: =I5-J5 -> 0 | L5: =IF(ABS(K5)<0.005,"OK","CHECK") -> OK
A6: P-0027 | B6: Nabd Internet | C6: اشتراك إنترنت فايبر 100 ميكا - شهر أيلول | D6: 1 | E6: 450000 | F6: IQD | H6: P-0027 | I6: =SUMIFS($E$5:$E$46,$A$5:$A$46,H6) -> 475000 | J6: =INDEX(Invoices!$L$5:$L$34,MATCH(H6,Invoices!$A$5:$A$34,0)) -> 475000 | K6: =I6-J6 -> 0 | L6: =IF(ABS(K6)<0.005,"OK","CHECK") -> OK
A7: P-0027 | B7: Nabd Internet | C7: إيجار راوتر | D7: 1 | E7: 25000 | F7: IQD | H7: P-0016 | I7: =SUMIFS($E$5:$E$46,$A$5:$A$46,H7) -> 950000 | J7: =INDEX(Invoices!$L$5:$L$34,MATCH(H7,Invoices!$A$5:$A$34,0)) -> 950000 | K7: =I7-J7 -> 0 | L7: =IF(ABS(K7)<0.005,"OK","CHECK") -> OK
A8: P-0016 | B8: Dijla Office Supplies | C8: ورق A4 (رزمة ٥٠٠ ورقة) | D8: 40 | E8: 300000 | F8: IQD | H8: P-0017 | I8: =SUMIFS($E$5:$E$46,$A$5:$A$46,H8) -> 521000 | J8: =INDEX(Invoices!$L$5:$L$34,MATCH(H8,Invoices!$A$5:$A$34,0)) -> 521000 | K8: =I8-J8 -> 0 | L8: =IF(ABS(K8)<0.005,"OK","CHECK") -> OK
A9: P-0016 | B9: Dijla Office Supplies | C9: حبر طابعة HP 85A | D9: 4 | E9: 380000 | F9: IQD | H9: P-0018 | I9: =SUMIFS($E$5:$E$46,$A$5:$A$46,H9) -> 6750000 | J9: =INDEX(Invoices!$L$5:$L$34,MATCH(H9,Invoices!$A$5:$A$34,0)) -> 6750000 | K9: =I9-J9 -> 0 | L9: =IF(ABS(K9)<0.005,"OK","CHECK") -> OK
A10: P-0016 | B10: Dijla Office Supplies | C10: ملفات بلاستيكية | D10: 100 | E10: 150000 | F10: IQD | H10: P-0020 | I10: =SUMIFS($E$5:$E$46,$A$5:$A$46,H10) -> 1208 | J10: =INDEX(Invoices!$L$5:$L$34,MATCH(H10,Invoices!$A$5:$A$34,0)) -> 1208 | K10: =I10-J10 -> 0 | L10: =IF(ABS(K10)<0.005,"OK","CHECK") -> OK
A11: P-0016 | B11: Dijla Office Supplies | C11: أقلام جاف (علبة) | D11: 10 | E11: 120000 | F11: IQD | H11: P-0026 | I11: =SUMIFS($E$5:$E$46,$A$5:$A$46,H11) -> 800000 | J11: =INDEX(Invoices!$L$5:$L$34,MATCH(H11,Invoices!$A$5:$A$34,0)) -> 800000 | K11: =I11-J11 -> 0 | L11: =IF(ABS(K11)<0.005,"OK","CHECK") -> OK
A12: P-0017 | B12: Al-Nakheel Foodstuffs | C12: شاي ٥٠٠ غم | D12: 24 | E12: 144000 | F12: IQD | H12: P-0021 | I12: =SUMIFS($E$5:$E$46,$A$5:$A$46,H12) -> 1060000 | J12: =INDEX(Invoices!$L$5:$L$34,MATCH(H12,Invoices!$A$5:$A$34,0)) -> 1060000 | K12: =I12-J12 -> 0 | L12: =IF(ABS(K12)<0.005,"OK","CHECK") -> OK
A13: P-0017 | B13: Al-Nakheel Foodstuffs | C13: سكر كيس ٥٠ كغم | D13: 2 | E13: 110000 | F13: IQD | H13: P-0022 | I13: =SUMIFS($E$5:$E$46,$A$5:$A$46,H13) -> 1060000 | J13: =INDEX(Invoices!$L$5:$L$34,MATCH(H13,Invoices!$A$5:$A$34,0)) -> 1060000 | K13: =I13-J13 -> 0 | L13: =IF(ABS(K13)<0.005,"OK","CHECK") -> OK
A14: P-0017 | B14: Al-Nakheel Foodstuffs | C14: ماء معدني (كارتون) | D14: 30 | E14: 135000 | F14: IQD | H14: P-0025 | I14: =SUMIFS($E$5:$E$46,$A$5:$A$46,H14) -> 200000 | J14: =INDEX(Invoices!$L$5:$L$34,MATCH(H14,Invoices!$A$5:$A$34,0)) -> 200000 | K14: =I14-J14 -> 0 | L14: =IF(ABS(K14)<0.005,"OK","CHECK") -> OK
A15: P-0017 | B15: Al-Nakheel Foodstuffs | C15: قهوة عربية ٥٠٠ غم | D15: 6 | E15: 132000 | F15: IQD | H15: P-0023 | I15: =SUMIFS($E$5:$E$46,$A$5:$A$46,H15) -> 488000 | J15: =INDEX(Invoices!$L$5:$L$34,MATCH(H15,Invoices!$A$5:$A$34,0)) -> 488000 | K15: =I15-J15 -> 0 | L15: =IF(ABS(K15)<0.005,"OK","CHECK") -> OK
A16: P-0018 | B16: Babel Maintenance | C16: تبديل كمبرسر منظومة التبريد المركزي | D16: 2 | E16: 3700000 | F16: IQD | H16: P-0028 | I16: =SUMIFS($E$5:$E$46,$A$5:$A$46,H16) -> 1025000 | J16: =INDEX(Invoices!$L$5:$L$34,MATCH(H16,Invoices!$A$5:$A$34,0)) -> 1025000 | K16: =I16-J16 -> 0 | L16: =IF(ABS(K16)<0.005,"OK","CHECK") -> OK
... A19: P-0020 | B19: Gulf Bridge IT | C19: Ubiquiti U6-Pro access point | D19: 3 | E19: 567 | F19: USD | H19: P-0030 | I19: =SUMIFS($E$5:$E$46,$A$5:$A$46,H19) -> 1500000 | J19: =INDEX(Invoices!$L$5:$L$34,MATCH(H19,Invoices!$A$5:$A$34,0)) -> 1500000 | K19: =I19-J19 -> 0 | L19: =IF(ABS(K19)<0.005,"OK","CHECK") -> OK
A20: P-0020 | B20: Gulf Bridge IT | C20: Cat6 cable, 305 m box | D20: 2 | E20: 291 | F20: USD
A21: P-0020 | B21: Gulf Bridge IT | C21: Installation and configuration | D21: 1 | E21: 350 | F21: USD
A22: P-0026 | B22: Al-Mansour Press | C22: بطاقات عمل (علبة ١٠٠) | D22: 5 | E22: 125000 | F22: IQD
A23: P-0026 | B23: Al-Mansour Press | C23: مطويات A4 ملونة | D23: 1000 | E23: 350000 | F23: IQD
A24: P-0026 | B24: Al-Mansour Press | C24: فولدرات مطبوعة | D24: 200 | E24: 350000 | F24: IQD
A25: P-0026 | B25: Al-Mansour Press | C25: خصم | E25: -25000 | F25: IQD
A26: P-0021 | B26: Dijla Office Supplies | C26: كرسي مكتب دوار | D26: 2 | E26: 570000 | F26: IQD
A27: P-0021 | B27: Dijla Office Supplies | C27: طاولة طابعة | D27: 1 | E27: 190000 | F27: IQD
A28: P-0021 | B28: Dijla Office Supplies | C28: ورق A4 (رزمة ٥٠٠ ورقة) | D28: 40 | E28: 300000 | F28: IQD
A29: P-0022 | B29: Dijla Office Supplies | C29: كرسي مكتب دوار | D29: 2 | E29: 570000 | F29: IQD
A30: P-0022 | B30: Dijla Office Supplies | C30: طاولة طابعة | D30: 1 | E30: 190000 | F30: IQD
A31: P-0022 | B31: Dijla Office Supplies | C31: ورق A4 (رزمة ٥٠٠ ورقة) | D31: 40 | E31: 300000 | F31: IQD
A32: P-0025 | B32: Al-Amin Auto Workshop | C32: تبديل فحمات أمامية | D32: 1 | E32: 85000 | F32: IQD
A33: P-0025 | B33: Al-Amin Auto Workshop | C33: زيت محرك + فلتر | D33: 1 | E33: 65000 | F33: IQD
A34: P-0025 | B34: Al-Amin Auto Workshop | C34: أجور تصليح | D34: 1 | E34: 50000 | F34: IQD
A35: P-0023 | B35: Al-Nakheel Foodstuffs | C35: شاي ٥٠٠ غم | D35: 24 | E35: 144000 | F35: IQD
A36: P-0023 | B36: Al-Nakheel Foodstuffs | C36: ماء معدني (كارتون) | D36: 40 | E36: 180000 | F36: IQD
A37: P-0023 | B37: Al-Nakheel Foodstuffs | C37: بسكويت (كارتون) | D37: 8 | E37: 164000 | F37: IQD
... A46: P-0030 | B46: Al-Karkh Accounting | C46: أتعاب إعداد الحسابات الختامية - الربع الثالث ٢٠٢٦ | D46: 1 | E46: 1500000 | F46: IQD

Sheet Summary
A1: Finance Ops Ledger Review: key figures
A2: Every figure is a formula over the Invoices sheet. These are the numbers shown in the report's top row.
A4: # | B4: Key figure | C4: Value | D4: Unit | E4: How it is calculated
A5: 1 | B5: Approved spend, September 2026 | C5: =SUMIFS(Invoices!$L$5:$L$34,Invoices!$K$5:$K$34,"IQD",Invoices!$M$5:$M$34,"approved",Invoices!$I$5:$I$34,"2026-09") -> 7715000 | D5: IQD | E5: Approved IQD invoices dated September
A6: 2 | B6: Approved spend, August 2026 | C6: =SUMIFS(Invoices!$L$5:$L$34,Invoices!$K$5:$K$34,"IQD",Invoices!$M$5:$M$34,"approved",Invoices!$I$5:$I$34,"2026-08") -> 7630000 | D6: IQD | E6: Approved IQD invoices dated August
A7: 3 | B7: Change September vs August | C7: =IF(C6=0,0,C5/C6-1) -> 0.011140236 | D7: % | E7: (Sep / Aug) − 1
A8: 4 | B8: Approved spend, September 2026 | C8: =SUMIFS(Invoices!$L$5:$L$34,Invoices!$K$5:$K$34,"USD",Invoices!$M$5:$M$34,"approved",Invoices!$I$5:$I$34,"2026-09") -> 2150.5 | D8: USD | E8: Approved USD invoices dated September
A9: 5 | B9: Approved spend, August 2026 | C9: =SUMIFS(Invoices!$L$5:$L$34,Invoices!$K$5:$K$34,"USD",Invoices!$M$5:$M$34,"approved",Invoices!$I$5:$I$34,"2026-08") -> 2415.5 | D9: USD | E9: Approved USD invoices dated August
A10: 6 | B10: Change September vs August (USD) | C10: =IF(C9=0,0,C8/C9-1) -> -0.10970813 | D10: % | E10: (Sep / Aug) − 1
A11: 7 | B11: Waiting for a decision | C11: =SUMIFS(Invoices!$L$5:$L$34,Invoices!$K$5:$K$34,"IQD",Invoices!$M$5:$M$34,"pending") -> 7438000 | D11: IQD | E11: All pending IQD invoices
A12: 8 | B12: Pending invoices (count) | C12: =COUNTIFS(Invoices!$M$5:$M$34,"pending") -> 3 | D12: invoices | E12: Count of pending
A13: 9 | B13: Pending as share of September approved spend | C13: =IF(C5=0,0,C11/C5) -> 0.96409592 | D13: % | E13: Pending IQD / September approved IQD
A14: 10 | B14: Duplicate payment blocked | C14: =SUMIFS(Invoices!$L$5:$L$34,Invoices!$M$5:$M$34,"rejected",Invoices!$R$5:$R$34,"Exact duplicate") -> 1060000 | D14: IQD | E14: Rejected invoice flagged as exact duplicate
A15: 11 | B15: Approved invoices, September (count) | C15: =COUNTIFS(Invoices!$M$5:$M$34,"approved",Invoices!$I$5:$I$34,"2026-09") -> 11 | D15: invoices | E15: IQD + USD
A16: 12 | B16: Fields read correctly in agent test | C16: 90 | D16: of 90 | E16: Input from reports/stage4/RESULTS.md (15 invoices × 6 fields)
A17: 13 | B17: Approved IQD spend, June–September | C17: =SUMIFS(Invoices!$L$5:$L$34,Invoices!$K$5:$K$34,"IQD",Invoices!$M$5:$M$34,"approved") -> 21985000 | D17: IQD | E17: All approved IQD
A18: 14 | B18: Approved USD spend, June–September | C18: =SUMIFS(Invoices!$L$5:$L$34,Invoices!$K$5:$K$34,"USD",Invoices!$M$5:$M$34,"approved") -> 5746 | D18: USD | E18: All approved USD

Sheet Monthly by Category
A1: Approved spend per month, by category
A2: Report sections 4 and 5. SUMIFS over the Invoices sheet; approved invoices only.
A4: IQD
A5: Category | B5: 2026-06 | C5: 2026-07 | D5: 2026-08 | E5: 2026-09 | F5: Total | G5: Share
A6: Maintenance | B6: =SUMIFS(Invoices!$L$5:$L$34,Invoices!$K$5:$K$34,"IQD",Invoices!$M$5:$M$34,"approved",Invoices!$E$5:$E$34,$A6,Invoices!$I$5:$I$34,"2026-06") -> 0 | C6: =SUMIFS(Invoices!$L$5:$L$34,Invoices!$K$5:$K$34,"IQD",Invoices!$M$5:$M$34,"approved",Invoices!$E$5:$E$34,$A6,Invoices!$I$5:$I$34,"2026-07") -> 2100000 | D6: =SUMIFS(Invoices!$L$5:$L$34,Invoices!$K$5:$K$34,"IQD",Invoices!$M$5:$M$34,"approved",Invoices!$E$5:$E$34,$A6,Invoices!$I$5:$I$34,"2026-08") -> 4150000 | E6: =SUMIFS(Invoices!$L$5:$L$34,Invoices!$K$5:$K$34,"IQD",Invoices!$M$5:$M$34,"approved",Invoices!$E$5:$E$34,$A6,Invoices!$I$5:$I$34,"2026-09") -> 1025000 | F6: =SUM(B6:E6) -> 7275000 | G6: =IF($F$13=0,0,F6/$F$13) -> 0.33090744
A7: Office supplies | B7: =SUMIFS(Invoices!$L$5:$L$34,Invoices!$K$5:$K$34,"IQD",Invoices!$M$5:$M$34,"approved",Invoices!$E$5:$E$34,$A7,Invoices!$I$5:$I$34,"2026-06") -> 0 | C7: =SUMIFS(Invoices!$L$5:$L$34,Invoices!$K$5:$K$34,"IQD",Invoices!$M$5:$M$34,"approved",Invoices!$E$5:$E$34,$A7,Invoices!$I$5:$I$34,"2026-07") -> 2130000 | D7: =SUMIFS(Invoices!$L$5:$L$34,Invoices!$K$5:$K$34,"IQD",Invoices!$M$5:$M$34,"approved",Invoices!$E$5:$E$34,$A7,Invoices!$I$5:$I$34,"2026-08") -> 1240000 | E7: =SUMIFS(Invoices!$L$5:$L$34,Invoices!$K$5:$K$34,"IQD",Invoices!$M$5:$M$34,"approved",Invoices!$E$5:$E$34,$A7,Invoices!$I$5:$I$34,"2026-09") -> 2010000 | F7: =SUM(B7:E7) -> 5380000 | G7: =IF($F$13=0,0,F7/$F$13) -> 0.2447123
A8: Utilities | B8: =SUMIFS(Invoices!$L$5:$L$34,Invoices!$K$5:$K$34,"IQD",Invoices!$M$5:$M$34,"approved",Invoices!$E$5:$E$34,$A8,Invoices!$I$5:$I$34,"2026-06") -> 870000 | C8: =SUMIFS(Invoices!$L$5:$L$34,Invoices!$K$5:$K$34,"IQD",Invoices!$M$5:$M$34,"approved",Invoices!$E$5:$E$34,$A8,Invoices!$I$5:$I$34,"2026-07") -> 900000 | D8: =SUMIFS(Invoices!$L$5:$L$34,Invoices!$K$5:$K$34,"IQD",Invoices!$M$5:$M$34,"approved",Invoices!$E$5:$E$34,$A8,Invoices!$I$5:$I$34,"2026-08") -> 945000 | E8: =SUMIFS(Invoices!$L$5:$L$34,Invoices!$K$5:$K$34,"IQD",Invoices!$M$5:$M$34,"approved",Invoices!$E$5:$E$34,$A8,Invoices!$I$5:$I$34,"2026-09") -> 1371000 | F8: =SUM(B8:E8) -> 4086000 | G8: =IF($F$13=0,0,F8/$F$13) -> 0.18585399
A9: Pantry | B9: =SUMIFS(Invoices!$L$5:$L$34,Invoices!$K$5:$K$34,"IQD",Invoices!$M$5:$M$34,"approved",Invoices!$E$5:$E$34,$A9,Invoices!$I$5:$I$34,"2026-06") -> 0 | C9: =SUMIFS(Invoices!$L$5:$L$34,Invoices!$K$5:$K$34,"IQD",Invoices!$M$5:$M$34,"approved",Invoices!$E$5:$E$34,$A9,Invoices!$I$5:$I$34,"2026-07") -> 640000 | D9: =SUMIFS(Invoices!$L$5:$L$34,Invoices!$K$5:$K$34,"IQD",Invoices!$M$5:$M$34,"approved",Invoices!$E$5:$E$34,$A9,Invoices!$I$5:$I$34,"2026-08") -> 1295000 | E9: =SUMIFS(Invoices!$L$5:$L$34,Invoices!$K$5:$K$34,"IQD",Invoices!$M$5:$M$34,"approved",Invoices!$E$5:$E$34,$A9,Invoices!$I$5:$I$34,"2026-09") -> 1009000 | F9: =SUM(B9:E9) -> 2944000 | G9: =IF($F$13=0,0,F9/$F$13) -> 0.13390948
A10: Professional fees | B10: =SUMIFS(Invoices!$L$5:$L$34,Invoices!$K$5:$K$34,"IQD",Invoices!$M$5:$M$34,"approved",Invoices!$E$5:$E$34,$A10,Invoices!$I$5:$I$34,"2026-06") -> 0 | C10: =SUMIFS(Invoices!$L$5:$L$34,Invoices!$K$5:$K$34,"IQD",Invoices!$M$5:$M$34,"approved",Invoices!$E$5:$E$34,$A10,Invoices!$I$5:$I$34,"2026-07") -> 0 | D10: =SUMIFS(Invoices!$L$5:$L$34,Invoices!$K$5:$K$34,"IQD",Invoices!$M$5:$M$34,"approved",Invoices!$E$5:$E$34,$A10,Invoices!$I$5:$I$34,"2026-08") -> 0 | E10: =SUMIFS(Invoices!$L$5:$L$34,Invoices!$K$5:$K$34,"IQD",Invoices!$M$5:$M$34,"approved",Invoices!$E$5:$E$34,$A10,Invoices!$I$5:$I$34,"2026-09") -> 1500000 | F10: =SUM(B10:E10) -> 1500000 | G10: =IF($F$13=0,0,F10/$F$13) -> 0.068228338
A11: Printing & marketing | B11: =SUMIFS(Invoices!$L$5:$L$34,Invoices!$K$5:$K$34,"IQD",Invoices!$M$5:$M$34,"approved",Invoices!$E$5:$E$34,$A11,Invoices!$I$5:$I$34,"2026-06") -> 0 | C11: =SUMIFS(Invoices!$L$5:$L$34,Invoices!$K$5:$K$34,"IQD",Invoices!$M$5:$M$34,"approved",Invoices!$E$5:$E$34,$A11,Invoices!$I$5:$I$34,"2026-07") -> 0 | D11: =SUMIFS(Invoices!$L$5:$L$34,Invoices!$K$5:$K$34,"IQD",Invoices!$M$5:$M$34,"approved",Invoices!$E$5:$E$34,$A11,Invoices!$I$5:$I$34,"2026-08") -> 0 | E11: =SUMIFS(Invoices!$L$5:$L$34,Invoices!$K$5:$K$34,"IQD",Invoices!$M$5:$M$34,"approved",Invoices!$E$5:$E$34,$A11,Invoices!$I$5:$I$34,"2026-09") -> 800000 | F11: =SUM(B11:E11) -> 800000 | G11: =IF($F$13=0,0,F11/$F$13) -> 0.036388447
A12: Vehicles | B12: =SUMIFS(Invoices!$L$5:$L$34,Invoices!$K$5:$K$34,"IQD",Invoices!$M$5:$M$34,"approved",Invoices!$E$5:$E$34,$A12,Invoices!$I$5:$I$34,"2026-06") -> 0 | C12: =SUMIFS(Invoices!$L$5:$L$34,Invoices!$K$5:$K$34,"IQD",Invoices!$M$5:$M$34,"approved",Invoices!$E$5:$E$34,$A12,Invoices!$I$5:$I$34,"2026-07") -> 0 | D12: =SUMIFS(Invoices!$L$5:$L$34,Invoices!$K$5:$K$34,"IQD",Invoices!$M$5:$M$34,"approved",Invoices!$E$5:$E$34,$A12,Invoices!$I$5:$I$34,"2026-08") -> 0 | E12: =SUMIFS(Invoices!$L$5:$L$34,Invoices!$K$5:$K$34,"IQD",Invoices!$M$5:$M$34,"approved",Invoices!$E$5:$E$34,$A12,Invoices!$I$5:$I$34,"2026-09") -> 0 | F12: =SUM(B12:E12) -> 0 | G12: =IF($F$13=0,0,F12/$F$13) -> 0
A13: Total IQD | B13: =SUM(B6:B12) -> 870000 | C13: =SUM(C6:C12) -> 5770000 | D13: =SUM(D6:D12) -> 7630000 | E13: =SUM(E6:E12) -> 7715000 | F13: =SUM(F6:F12) -> 21985000 | G13: =SUM(G6:G12) -> 1
A14: Change vs previous month | D14: =IF(C13=0,0,D13/C13-1) -> 0.32235702 | E14: =IF(D13=0,0,E13/D13-1) -> 0.011140236
A15: June holds one seeded history invoice only (Ur Generator); not a full month.
A17: USD
A18: Category | B18: 2026-06 | C18: 2026-07 | D18: 2026-08 | E18: 2026-09 | F18: Total
A19: IT (USD) | B19: =SUMIFS(Invoices!$L$5:$L$34,Invoices!$K$5:$K$34,"USD",Invoices!$M$5:$M$34,"approved",Invoices!$I$5:$I$34,"2026-06") -> 0 | C19: =SUMIFS(Invoices!$L$5:$L$34,Invoices!$K$5:$K$34,"USD",Invoices!$M$5:$M$34,"approved",Invoices!$I$5:$I$34,"2026-07") -> 1180 | D19: =SUMIFS(Invoices!$L$5:$L$34,Invoices!$K$5:$K$34,"USD",Invoices!$M$5:$M$34,"approved",Invoices!$I$5:$I$34,"2026-08") -> 2415.5 | E19: =SUMIFS(Invoices!$L$5:$L$34,Invoices!$K$5:$K$34,"USD",Invoices!$M$5:$M$34,"approved",Invoices!$I$5:$I$34,"2026-09") -> 2150.5 | F19: =SUM(B19:E19) -> 5746
A20: Change vs previous month | D20: =IF(C19=0,0,D19/C19-1) -> 1.0470339 | E20: =IF(D19=0,0,E19/D19-1) -> -0.10970813

Sheet Suppliers
A1: Supplier analysis
A2: Report sections 6 and 7. Approved and pending totals, average invoice, and approved spend per month.
A4: Supplier | B4: Category | C4: Currency | D4: Approved total | E4: Approved invoices | F4: Average invoice | G4: Pending total | H4: Approved + pending | I4: Share of approved | J4: 2026-06 | K4: 2026-07 | L4: 2026-08 | M4: 2026-09
A5: Babel Maintenance | B5: Maintenance | C5: IQD | D5: =SUMIFS(Invoices!$L$5:$L$34,Invoices!$D$5:$D$34,$A5,Invoices!$M$5:$M$34,"approved") -> 7275000 | E5: =COUNTIFS(Invoices!$D$5:$D$34,$A5,Invoices!$M$5:$M$34,"approved") -> 4 | F5: =IF(E5=0,0,D5/E5) -> 1818750 | G5: =SUMIFS(Invoices!$L$5:$L$34,Invoices!$D$5:$D$34,$A5,Invoices!$M$5:$M$34,"pending") -> 6750000 | H5: =D5+G5 -> 14025000 | I5: =IF(SUMIFS(Invoices!$L$5:$L$34,Invoices!$K$5:$K$34,"IQD",Invoices!$M$5:$M$34,"approved")=0,0,D5/SUMIFS(Invoices!$L$5:$L$34,Invoices!$K$5:$K$34,"IQD",Invoices!$M$5:$M$34,"approved")) -> 0.33090744 | J5: =SUMIFS(Invoices!$L$5:$L$34,Invoices!$D$5:$D$34,$A5,Invoices!$M$5:$M$34,"approved",Invoices!$I$5:$I$34,"2026-06") -> 0 | K5: =SUMIFS(Invoices!$L$5:$L$34,Invoices!$D$5:$D$34,$A5,Invoices!$M$5:$M$34,"approved",Invoices!$I$5:$I$34,"2026-07") -> 2100000 | L5: =SUMIFS(Invoices!$L$5:$L$34,Invoices!$D$5:$D$34,$A5,Invoices!$M$5:$M$34,"approved",Invoices!$I$5:$I$34,"2026-08") -> 4150000 | M5: =SUMIFS(Invoices!$L$5:$L$34,Invoices!$D$5:$D$34,$A5,Invoices!$M$5:$M$34,"approved",Invoices!$I$5:$I$34,"2026-09") -> 1025000
A6: Dijla Office Supplies | B6: Office supplies | C6: IQD | D6: =SUMIFS(Invoices!$L$5:$L$34,Invoices!$D$5:$D$34,$A6,Invoices!$M$5:$M$34,"approved") -> 5380000 | E6: =COUNTIFS(Invoices!$D$5:$D$34,$A6,Invoices!$M$5:$M$34,"approved") -> 5 | F6: =IF(E6=0,0,D6/E6) -> 1076000 | G6: =SUMIFS(Invoices!$L$5:$L$34,Invoices!$D$5:$D$34,$A6,Invoices!$M$5:$M$34,"pending") -> 0 | H6: =D6+G6 -> 5380000 | I6: =IF(SUMIFS(Invoices!$L$5:$L$34,Invoices!$K$5:$K$34,"IQD",Invoices!$M$5:$M$34,"approved")=0,0,D6/SUMIFS(Invoices!$L$5:$L$34,Invoices!$K$5:$K$34,"IQD",Invoices!$M$5:$M$34,"approved")) -> 0.2447123 | J6: =SUMIFS(Invoices!$L$5:$L$34,Invoices!$D$5:$D$34,$A6,Invoices!$M$5:$M$34,"approved",Invoices!$I$5:$I$34,"2026-06") -> 0 | K6: =SUMIFS(Invoices!$L$5:$L$34,Invoices!$D$5:$D$34,$A6,Invoices!$M$5:$M$34,"approved",Invoices!$I$5:$I$34,"2026-07") -> 2130000 | L6: =SUMIFS(Invoices!$L$5:$L$34,Invoices!$D$5:$D$34,$A6,Invoices!$M$5:$M$34,"approved",Invoices!$I$5:$I$34,"2026-08") -> 1240000 | M6: =SUMIFS(Invoices!$L$5:$L$34,Invoices!$D$5:$D$34,$A6,Invoices!$M$5:$M$34,"approved",Invoices!$I$5:$I$34,"2026-09") -> 2010000
A7: Ur Generator | B7: Utilities | C7: IQD | D7: =SUMIFS(Invoices!$L$5:$L$34,Invoices!$D$5:$D$34,$A7,Invoices!$M$5:$M$34,"approved") -> 3611000 | E7: =COUNTIFS(Invoices!$D$5:$D$34,$A7,Invoices!$M$5:$M$34,"approved") -> 4 | F7: =IF(E7=0,0,D7/E7) -> 902750 | G7: =SUMIFS(Invoices!$L$5:$L$34,Invoices!$D$5:$D$34,$A7,Invoices!$M$5:$M$34,"pending") -> 0 | H7: =D7+G7 -> 3611000 | I7: =IF(SUMIFS(Invoices!$L$5:$L$34,Invoices!$K$5:$K$34,"IQD",Invoices!$M$5:$M$34,"approved")=0,0,D7/SUMIFS(Invoices!$L$5:$L$34,Invoices!$K$5:$K$34,"IQD",Invoices!$M$5:$M$34,"approved")) -> 0.16424835 | J7: =SUMIFS(Invoices!$L$5:$L$34,Invoices!$D$5:$D$34,$A7,Invoices!$M$5:$M$34,"approved",Invoices!$I$5:$I$34,"2026-06") -> 870000 | K7: =SUMIFS(Invoices!$L$5:$L$34,Invoices!$D$5:$D$34,$A7,Invoices!$M$5:$M$34,"approved",Invoices!$I$5:$I$34,"2026-07") -> 900000 | L7: =SUMIFS(Invoices!$L$5:$L$34,Invoices!$D$5:$D$34,$A7,Invoices!$M$5:$M$34,"approved",Invoices!$I$5:$I$34,"2026-08") -> 945000 | M7: =SUMIFS(Invoices!$L$5:$L$34,Invoices!$D$5:$D$34,$A7,Invoices!$M$5:$M$34,"approved",Invoices!$I$5:$I$34,"2026-09") -> 896000
A8: Al-Nakheel Foodstuffs | B8: Pantry | C8: IQD | D8: =SUMIFS(Invoices!$L$5:$L$34,Invoices!$D$5:$D$34,$A8,Invoices!$M$5:$M$34,"approved") -> 2944000 | E8: =COUNTIFS(Invoices!$D$5:$D$34,$A8,Invoices!$M$5:$M$34,"approved") -> 5 | F8: =IF(E8=0,0,D8/E8) -> 588800 | G8: =SUMIFS(Invoices!$L$5:$L$34,Invoices!$D$5:$D$34,$A8,Invoices!$M$5:$M$34,"pending") -> 488000 | H8: =D8+G8 -> 3432000 | I8: =IF(SUMIFS(Invoices!$L$5:$L$34,Invoices!$K$5:$K$34,"IQD",Invoices!$M$5:$M$34,"approved")=0,0,D8/SUMIFS(Invoices!$L$5:$L$34,Invoices!$K$5:$K$34,"IQD",Invoices!$M$5:$M$34,"approved")) -> 0.13390948 | J8: =SUMIFS(Invoices!$L$5:$L$34,Invoices!$D$5:$D$34,$A8,Invoices!$M$5:$M$34,"approved",Invoices!$I$5:$I$34,"2026-06") -> 0 | K8: =SUMIFS(Invoices!$L$5:$L$34,Invoices!$D$5:$D$34,$A8,Invoices!$M$5:$M$34,"approved",Invoices!$I$5:$I$34,"2026-07") -> 640000 | L8: =SUMIFS(Invoices!$L$5:$L$34,Invoices!$D$5:$D$34,$A8,Invoices!$M$5:$M$34,"approved",Invoices!$I$5:$I$34,"2026-08") -> 1295000 | M8: =SUMIFS(Invoices!$L$5:$L$34,Invoices!$D$5:$D$34,$A8,Invoices!$M$5:$M$34,"approved",Invoices!$I$5:$I$34,"2026-09") -> 1009000
A9: Al-Karkh Accounting | B9: Professional fees | C9: IQD | D9: =SUMIFS(Invoices!$L$5:$L$34,Invoices!$D$5:$D$34,$A9,Invoices!$M$5:$M$34,"approved") -> 1500000 | E9: =COUNTIFS(Invoices!$D$5:$D$34,$A9,Invoices!$M$5:$M$34,"approved") -> 1 | F9: =IF(E9=0,0,D9/E9) -> 1500000 | G9: =SUMIFS(Invoices!$L$5:$L$34,Invoices!$D$5:$D$34,$A9,Invoices!$M$5:$M$34,"pending") -> 0 | H9: =D9+G9 -> 1500000 | I9: =IF(SUMIFS(Invoices!$L$5:$L$34,Invoices!$K$5:$K$34,"IQD",Invoices!$M$5:$M$34,"approved")=0,0,D9/SUMIFS(Invoices!$L$5:$L$34,Invoices!$K$5:$K$34,"IQD",Invoices!$M$5:$M$34,"approved")) -> 0.068228338 | J9: =SUMIFS(Invoices!$L$5:$L$34,Invoices!$D$5:$D$34,$A9,Invoices!$M$5:$M$34,"approved",Invoices!$I$5:$I$34,"2026-06") -> 0 | K9: =SUMIFS(Invoices!$L$5:$L$34,Invoices!$D$5:$D$34,$A9,Invoices!$M$5:$M$34,"approved",Invoices!$I$5:$I$34,"2026-07") -> 0 | L9: =SUMIFS(Invoices!$L$5:$L$34,Invoices!$D$5:$D$34,$A9,Invoices!$M$5:$M$34,"approved",Invoices!$I$5:$I$34,"2026-08") -> 0 | M9: =SUMIFS(Invoices!$L$5:$L$34,Invoices!$D$5:$D$34,$A9,Invoices!$M$5:$M$34,"approved",Invoices!$I$5:$I$34,"2026-09") -> 1500000
A10: Al-Mansour Press | B10: Printing & marketing | C10: IQD | D10: =SUMIFS(Invoices!$L$5:$L$34,Invoices!$D$5:$D$34,$A10,Invoices!$M$5:$M$34,"approved") -> 800000 | E10: =COUNTIFS(Invoices!$D$5:$D$34,$A10,Invoices!$M$5:$M$34,"approved") -> 1 | F10: =IF(E10=0,0,D10/E10) -> 800000 | G10: =SUMIFS(Invoices!$L$5:$L$34,Invoices!$D$5:$D$34,$A10,Invoices!$M$5:$M$34,"pending") -> 0 | H10: =D10+G10 -> 800000 | I10: =IF(SUMIFS(Invoices!$L$5:$L$34,Invoices!$K$5:$K$34,"IQD",Invoices!$M$5:$M$34,"approved")=0,0,D10/SUMIFS(Invoices!$L$5:$L$34,Invoices!$K$5:$K$34,"IQD",Invoices!$M$5:$M$34,"approved")) -> 0.036388447 | J10: =SUMIFS(Invoices!$L$5:$L$34,Invoices!$D$5:$D$34,$A10,Invoices!$M$5:$M$34,"approved",Invoices!$I$5:$I$34,"2026-06") -> 0 | K10: =SUMIFS(Invoices!$L$5:$L$34,Invoices!$D$5:$D$34,$A10,Invoices!$M$5:$M$34,"approved",Invoices!$I$5:$I$34,"2026-07") -> 0 | L10: =SUMIFS(Invoices!$L$5:$L$34,Invoices!$D$5:$D$34,$A10,Invoices!$M$5:$M$34,"approved",Invoices!$I$5:$I$34,"2026-08") -> 0 | M10: =SUMIFS(Invoices!$L$5:$L$34,Invoices!$D$5:$D$34,$A10,Invoices!$M$5:$M$34,"approved",Invoices!$I$5:$I$34,"2026-09") -> 800000
A11: Nabd Internet | B11: Utilities | C11: IQD | D11: =SUMIFS(Invoices!$L$5:$L$34,Invoices!$D$5:$D$34,$A11,Invoices!$M$5:$M$34,"approved") -> 475000 | E11: =COUNTIFS(Invoices!$D$5:$D$34,$A11,Invoices!$M$5:$M$34,"approved") -> 1 | F11: =IF(E11=0,0,D11/E11) -> 475000 | G11: =SUMIFS(Invoices!$L$5:$L$34,Invoices!$D$5:$D$34,$A11,Invoices!$M$5:$M$34,"pending") -> 0 | H11: =D11+G11 -> 475000 | I11: =IF(SUMIFS(Invoices!$L$5:$L$34,Invoices!$K$5:$K$34,"IQD",Invoices!$M$5:$M$34,"approved")=0,0,D11/SUMIFS(Invoices!$L$5:$L$34,Invoices!$K$5:$K$34,"IQD",Invoices!$M$5:$M$34,"approved")) -> 0.02160564 | J11: =SUMIFS(Invoices!$L$5:$L$34,Invoices!$D$5:$D$34,$A11,Invoices!$M$5:$M$34,"approved",Invoices!$I$5:$I$34,"2026-06") -> 0 | K11: =SUMIFS(Invoices!$L$5:$L$34,Invoices!$D$5:$D$34,$A11,Invoices!$M$5:$M$34,"approved",Invoices!$I$5:$I$34,"2026-07") -> 0 | L11: =SUMIFS(Invoices!$L$5:$L$34,Invoices!$D$5:$D$34,$A11,Invoices!$M$5:$M$34,"approved",Invoices!$I$5:$I$34,"2026-08") -> 0 | M11: =SUMIFS(Invoices!$L$5:$L$34,Invoices!$D$5:$D$34,$A11,Invoices!$M$5:$M$34,"approved",Invoices!$I$5:$I$34,"2026-09") -> 475000
A12: Al-Amin Auto Workshop | B12: Vehicles | C12: IQD | D12: =SUMIFS(Invoices!$L$5:$L$34,Invoices!$D$5:$D$34,$A12,Invoices!$M$5:$M$34,"approved") -> 0 | E12: =COUNTIFS(Invoices!$D$5:$D$34,$A12,Invoices!$M$5:$M$34,"approved") -> 0 | F12: =IF(E12=0,0,D12/E12) -> 0 | G12: =SUMIFS(Invoices!$L$5:$L$34,Invoices!$D$5:$D$34,$A12,Invoices!$M$5:$M$34,"pending") -> 200000 | H12: =D12+G12 -> 200000 | I12: =IF(SUMIFS(Invoices!$L$5:$L$34,Invoices!$K$5:$K$34,"IQD",Invoices!$M$5:$M$34,"approved")=0,0,D12/SUMIFS(Invoices!$L$5:$L$34,Invoices!$K$5:$K$34,"IQD",Invoices!$M$5:$M$34,"approved")) -> 0 | J12: =SUMIFS(Invoices!$L$5:$L$34,Invoices!$D$5:$D$34,$A12,Invoices!$M$5:$M$34,"approved",Invoices!$I$5:$I$34,"2026-06") -> 0 | K12: =SUMIFS(Invoices!$L$5:$L$34,Invoices!$D$5:$D$34,$A12,Invoices!$M$5:$M$34,"approved",Invoices!$I$5:$I$34,"2026-07") -> 0 | L12: =SUMIFS(Invoices!$L$5:$L$34,Invoices!$D$5:$D$34,$A12,Invoices!$M$5:$M$34,"approved",Invoices!$I$5:$I$34,"2026-08") -> 0 | M12: =SUMIFS(Invoices!$L$5:$L$34,Invoices!$D$5:$D$34,$A12,Invoices!$M$5:$M$34,"approved",Invoices!$I$5:$I$34,"2026-09") -> 0
A13: Total IQD | D13: =SUM(D5:D12) -> 21985000 | E13: =SUM(E5:E12) -> 21 | G13: =SUM(G5:G12) -> 7438000 | H13: =SUM(H5:H12) -> 29423000 | J13: =SUM(J5:J12) -> 870000 | K13: =SUM(K5:K12) -> 5770000 | L13: =SUM(L5:L12) -> 7630000 | M13: =SUM(M5:M12) -> 7715000
A14: Gulf Bridge IT | B14: IT (USD) | C14: USD | D14: =SUMIFS(Invoices!$L$5:$L$34,Invoices!$D$5:$D$34,$A14,Invoices!$M$5:$M$34,"approved") -> 5746 | E14: =COUNTIFS(Invoices!$D$5:$D$34,$A14,Invoices!$M$5:$M$34,"approved") -> 5 | F14: =IF(E14=0,0,D14/E14) -> 1149.2 | G14: =SUMIFS(Invoices!$L$5:$L$34,Invoices!$D$5:$D$34,$A14,Invoices!$M$5:$M$34,"pending") -> 0 | H14: =D14+G14 -> 5746 | I14: n/a (USD) | J14: =SUMIFS(Invoices!$L$5:$L$34,Invoices!$D$5:$D$34,$A14,Invoices!$M$5:$M$34,"approved",Invoices!$I$5:$I$34,"2026-06") -> 0 | K14: =SUMIFS(Invoices!$L$5:$L$34,Invoices!$D$5:$D$34,$A14,Invoices!$M$5:$M$34,"approved",Invoices!$I$5:$I$34,"2026-07") -> 1180 | L14: =SUMIFS(Invoices!$L$5:$L$34,Invoices!$D$5:$D$34,$A14,Invoices!$M$5:$M$34,"approved",Invoices!$I$5:$I$34,"2026-08") -> 2415.5 | M14: =SUMIFS(Invoices!$L$5:$L$34,Invoices!$D$5:$D$34,$A14,Invoices!$M$5:$M$34,"approved",Invoices!$I$5:$I$34,"2026-09") -> 2150.5

Sheet Decision Queue
A1: Decision queue and September what-if
A2: Report sections 1 and 2. Change the yellow cells (Y/N) to see September's total if a pending invoice were approved.
A4: Ref | B4: Supplier | C4: Invoice date | D4: Amount (IQD) | E4: Status | F4: Warning | G4: Detail | H4: Recommended next step | I4: Include in what-if? (Y/N)
A5: P-0018 | B5: =INDEX(Invoices!$D$5:$D$34,MATCH($A5,Invoices!$A$5:$A$34,0)) -> Babel Maintenance | C5: =INDEX(Invoices!$H$5:$H$34,MATCH($A5,Invoices!$A$5:$A$34,0)) -> 46273 | D5: =INDEX(Invoices!$L$5:$L$34,MATCH($A5,Invoices!$A$5:$A$34,0)) -> 6750000 | E5: =INDEX(Invoices!$M$5:$M$34,MATCH($A5,Invoices!$A$5:$A$34,0)) -> pending | F5: =INDEX(Invoices!$R$5:$R$34,MATCH($A5,Invoices!$A$5:$A$34,0)) -> Unusually large | G5: =INDEX(Invoices!$S$5:$S$34,MATCH($A5,Invoices!$A$5:$A$34,0)) -> 3.2x supplier average of 2,083,333 IQD | H5: Hold · verify work order, labour detail and a second quote | I5: N
A6: P-0024 | B6: =INDEX(Invoices!$D$5:$D$34,MATCH($A6,Invoices!$A$5:$A$34,0)) -> Al-Nakheel Foodstuffs | C6: =INDEX(Invoices!$H$5:$H$34,MATCH($A6,Invoices!$A$5:$A$34,0)) -> 46288 | D6: =INDEX(Invoices!$L$5:$L$34,MATCH($A6,Invoices!$A$5:$A$34,0)) -> 488000 | E6: =INDEX(Invoices!$M$5:$M$34,MATCH($A6,Invoices!$A$5:$A$34,0)) -> pending | F6: =INDEX(Invoices!$R$5:$R$34,MATCH($A6,Invoices!$A$5:$A$34,0)) -> Probable duplicate | G6: =INDEX(Invoices!$S$5:$S$34,MATCH($A6,Invoices!$A$5:$A$34,0)) -> Same supplier & amount as P-0023, 2 days apart, identical items | H6: Hold · confirm whether two deliveries arrived; reject if re-issue | I6: N
A7: P-0025 | B7: =INDEX(Invoices!$D$5:$D$34,MATCH($A7,Invoices!$A$5:$A$34,0)) -> Al-Amin Auto Workshop | C7: =INDEX(Invoices!$H$5:$H$34,MATCH($A7,Invoices!$A$5:$A$34,0)) -> 46283 | D7: =INDEX(Invoices!$L$5:$L$34,MATCH($A7,Invoices!$A$5:$A$34,0)) -> 200000 | E7: =INDEX(Invoices!$M$5:$M$34,MATCH($A7,Invoices!$A$5:$A$34,0)) -> pending | F7: =INDEX(Invoices!$R$5:$R$34,MATCH($A7,Invoices!$A$5:$A$34,0)) -> Weekend date; No tax number | G7: =INDEX(Invoices!$S$5:$S$34,MATCH($A7,Invoices!$A$5:$A$34,0)) -> Friday 18 Sep 2026; no tax number printed; new supplier | H7: Get tax number, then approve | I7: N
A8: P-0022 | B8: =INDEX(Invoices!$D$5:$D$34,MATCH($A8,Invoices!$A$5:$A$34,0)) -> Dijla Office Supplies | C8: =INDEX(Invoices!$H$5:$H$34,MATCH($A8,Invoices!$A$5:$A$34,0)) -> 46281 | D8: =INDEX(Invoices!$L$5:$L$34,MATCH($A8,Invoices!$A$5:$A$34,0)) -> 1060000 | E8: =INDEX(Invoices!$M$5:$M$34,MATCH($A8,Invoices!$A$5:$A$34,0)) -> rejected | F8: =INDEX(Invoices!$R$5:$R$34,MATCH($A8,Invoices!$A$5:$A$34,0)) -> Exact duplicate | G8: =INDEX(Invoices!$S$5:$S$34,MATCH($A8,Invoices!$A$5:$A$34,0)) -> Same invoice no. DJ-2026-0952 as P-0021 (photo of same paper invoice) | H8: Done · rejected as duplicate of L-0020
B10: September approved (IQD) | D10: =Summary!C5 -> 7715000
B11: Pending included in what-if | D11: =SUMIFS(D5:D7,I5:I7,"Y") -> 0
B12: Projected September (IQD) | D12: =D10+D11 -> 7715000
B13: Change vs August | D13: =IF(Summary!C6=0,0,D12/Summary!C6-1) -> 0.011140236
B15: Legend: yellow cells are the only cells to edit (Y = include the invoice as if approved). Green = looked up from Invoices.

Sheet Control Checks
A1: Warning rules: what the agent caught
A2: Report section 8. Counts September invoices whose staging warning contains each rule name.
A4: Rule | B4: What it checks | C4: Triggered (Sep) | D4: Invoices | E4: What to do
A5: Exact duplicate | B5: Same supplier and same invoice number as another entry | C5: =COUNTIFS(Invoices!$R$5:$R$34,"*"&A5&"*",Invoices!$I$5:$I$34,"2026-09") -> 1 | D5: P-0022 | E5: Approve only one copy.
A6: Probable duplicate | B6: Same supplier and same amount within 7 days | C6: =COUNTIFS(Invoices!$R$5:$R$34,"*"&A6&"*",Invoices!$I$5:$I$34,"2026-09") -> 1 | D6: P-0024 | E6: Compare items or ask the supplier.
A7: Unusually large | B7: More than 2× the supplier's normal amount (needs 3 approved invoices) | C7: =COUNTIFS(Invoices!$R$5:$R$34,"*"&A7&"*",Invoices!$I$5:$I$34,"2026-09") -> 1 | D7: P-0018 | E7: Check against the work or purchase order.
A8: Weekend date | B8: Dated Friday or Saturday | C8: =COUNTIFS(Invoices!$R$5:$R$34,"*"&A8&"*",Invoices!$I$5:$I$34,"2026-09") -> 1 | D8: P-0025 | E8: Confirm the delivery or service happened.
A9: No tax number | B9: Supplier tax number not printed | C9: =COUNTIFS(Invoices!$R$5:$R$34,"*"&A9&"*",Invoices!$I$5:$I$34,"2026-09") -> 1 | D9: P-0025 | E9: Ask the supplier for it.
A10: Future date | B10: Dated after today | C10: =COUNTIFS(Invoices!$R$5:$R$34,"*"&A10&"*",Invoices!$I$5:$I$34,"2026-09") -> 0 | D10: — | E10: Usually day/month swapped. Note: a swap giving a valid past date is NOT caught.
A11: Items don't add up | B11: Line items don't match the printed total | C11: =COUNTIFS(Invoices!$R$5:$R$34,"*"&A11&"*",Invoices!$I$5:$I$34,"2026-09") -> 0 | D11: — | E11: Check the original invoice.
A13: Total warnings | C13: =SUM(C5:C11) -> 5
A15: Agent test score (input from reports/stage4/RESULTS.md)
A16: Planted problems caught | C16: 5
A17: Planted problems missed | C17: 0
A18: False alarms | C18: 0
A19: Fields read correctly | C19: 90
A20: Fields checked | C20: 90
A21: Line-item check (all September invoices add up) | C21: =IF(COUNTIF('Line Items'!L5:L20,"CHECK")=0,"OK","CHECK") -> OK

Sheet Recurring Costs
A1: Recurring-cost calendar
A2: Strategy decision 5. Monthly amounts are the latest approved invoice; frequency is an analyst assumption (blue).
A4: Cost | B4: Supplier | C4: Latest ref | D4: Latest amount | E4: Currency | F4: Times per year | G4: Annual estimate | H4: Next due (assumption)
A5: Generator subscription | B5: Ur Generator | C5: P-0019 | D5: =INDEX(Invoices!$L$5:$L$34,MATCH(C5,Invoices!$A$5:$A$34,0)) -> 896000 | E5: =INDEX(Invoices!$K$5:$K$34,MATCH(C5,Invoices!$A$5:$A$34,0)) -> IQD | F5: 12 | G5: =D5*F5 -> 10752000 | H5: Monthly
A6: Fibre internet + router | B6: Nabd Internet | C6: P-0027 | D6: =INDEX(Invoices!$L$5:$L$34,MATCH(C6,Invoices!$A$5:$A$34,0)) -> 475000 | E6: =INDEX(Invoices!$K$5:$K$34,MATCH(C6,Invoices!$A$5:$A$34,0)) -> IQD | F6: 12 | G6: =D6*F6 -> 5700000 | H6: Monthly
A7: Quarterly accounting fee | B7: Al-Karkh Accounting | C7: P-0030 | D7: =INDEX(Invoices!$L$5:$L$34,MATCH(C7,Invoices!$A$5:$A$34,0)) -> 1500000 | E7: =INDEX(Invoices!$K$5:$K$34,MATCH(C7,Invoices!$A$5:$A$34,0)) -> IQD | F7: 4 | G7: =D7*F7 -> 6000000 | H7: End of December 2026
A8: Microsoft 365 + antivirus (5 users) | B8: Gulf Bridge IT | C8: P-0029 | D8: =INDEX(Invoices!$L$5:$L$34,MATCH(C8,Invoices!$A$5:$A$34,0)) -> 942.5 | E8: =INDEX(Invoices!$K$5:$K$34,MATCH(C8,Invoices!$A$5:$A$34,0)) -> USD | F8: 1 | G8: =D8*F8 -> 942.5 | H8: September 2027
A10: Fixed monthly IQD (generator + internet) | G10: =D5+D6 -> 1371000
A11: Annual IQD (generator + internet + accounting) | G11: =G5+G6+G7 -> 22452000
A13: Note: P-0029 is the annual-licence invoice (942.50 USD). Yellow cells are assumptions you can change.
